[{"month": "2023-07-15", "top_countries": [["Sri Lanka", 21898], ["Nepal", 20859], ["Ghana", 12642], ["Mozambique", 12341], ["Kenya", 9064], ["India", 8874], ["Nicaragua", 8779], ["Nigeria", 7982], ["Malawi", 6381], ["United States of America", 5658], ["Uganda", 3901], ["C\u00f4te d'Ivoire", 3582], ["Tanzania", 3268], ["Mexico", 2630], ["Ecuador", 2556]]}, {"month": "2023-08-15", "top_countries": [["India", 75439], ["Somalia", 60394], ["Mali", 26630], ["Kenya", 26362], ["Nepal", 18280], ["Nigeria", 18094], ["Bangladesh", 17343], ["Nicaragua", 10646], ["Malawi", 9607], ["Philippines", 4880], ["Brazil", 4474], ["Ethiopia", 4312], ["Tanzania", 4275], ["Ghana", 3986], ["Madagascar", 2832]]}, {"month": "2023-09-15", "top_countries": [["Somalia", 99913], ["Kenya", 36053], ["Ethiopia", 23995], ["India", 20331], ["Morocco", 16919], ["Tanzania", 13160], ["Nigeria", 5622], ["Brazil", 4614], ["Nepal", 2268], ["Malawi", 1940], ["Sierra Leone", 1784], ["Mali", 1716], ["Philippines", 1655], ["Ghana", 1361], ["Libya", 982]]}]